<?xml version="1.0" encoding="utf-8"?>
<SoundBanksInfo Platform="Windows" BasePlatform="Windows" SchemaVersion="16" SoundBankVersion="150">
	<SoundBanks>
		<SoundBank Id="2782713051" Type="User" Language="SFX" Hash="{276DF46D-0B29-EE74-68D2-6918190919BC}">
			<ShortName>Leve2</ShortName>
			<Path>Leve2.bnk</Path>
			<Media>
				<File Id="760915427" Language="SFX" Streaming="false" Location="Memory">
					<ShortName>Break.wav</ShortName>
					<CachePath>SFX/Break_818F3B66.wem</CachePath>
				</File>
			</Media>
			<Events>
				<Event Id="2859270420" Name="Pause_Level2" DurationType="OneShot" DurationMin="0" DurationMax="0"/>
				<Event Id="3659125942" Name="Play_Level2" DurationType="OneShot" DurationMin="182.21053" DurationMax="182.21053">
					<MediaRefs>
						<MediaRef Id="760915427"/>
					</MediaRefs>
				</Event>
				<Event Id="3265051675" Name="Resume_Level2" DurationType="OneShot" DurationMin="0" DurationMax="0"/>
				<Event Id="3077303045" Name="StopLevel2" DurationType="OneShot" DurationMin="0" DurationMax="0"/>
			</Events>
		</SoundBank>
	</SoundBanks>
	<FileHash>{F709AE83-A0BE-7407-A3AD-ADD901B23B04}</FileHash>
</SoundBanksInfo>
